README.md
setup.py
rofi_browser_bookmarks/BookmarksParserFactory.py
rofi_browser_bookmarks/BrowserNotFoundException.py
rofi_browser_bookmarks/ChromeBookmarksParser.py
rofi_browser_bookmarks/FormatColumns.py
rofi_browser_bookmarks/__init__.py
rofi_browser_bookmarks.egg-info/PKG-INFO
rofi_browser_bookmarks.egg-info/SOURCES.txt
rofi_browser_bookmarks.egg-info/dependency_links.txt
rofi_browser_bookmarks.egg-info/entry_points.txt
rofi_browser_bookmarks.egg-info/requires.txt
rofi_browser_bookmarks.egg-info/top_level.txt