Metadata-Version: 2.1
Name: rofi-browser-bookmarks
Version: 0.1.2
Summary: rofi prompt that displays browser bookmarks to open
Home-page: https://github.com/derekhamilton/rofi-browser-bookmarks
Author: Derek Hamilton
License: UNKNOWN
Project-URL: Source, https://github.com/derekhamilton/rofi-browser-bookmarks
Keywords: git git-cli git-client linux fzf cli command-line
Platform: UNKNOWN
Classifier: Development Status :: 4 - Beta
Classifier: Intended Audience :: Developers
Classifier: License :: OSI Approved :: MIT License
Classifier: Programming Language :: Python :: 3.5
Classifier: Programming Language :: Python :: 3.6
Classifier: Programming Language :: Python :: 3.7
Requires-Python: >=3.5
